{
  "routing_rules": [
    {
      "specialty": "anesthesia",
      "keywords": ["麻醉", "气道", "ASA", "禁食", "苏醒", "插管", "围术期", "镇痛"]
    },
    {
      "specialty": "cardiology",
      "keywords": ["心电图", "胸痛", "心律", "ST", "血压", "心衰", "灌注", "抗凝", "心源性"]
    },
    {
      "specialty": "hepatobiliary",
      "keywords": ["黄疸", "胆道", "肝", "胰", "感染", "ERCP", "引流", "胆红素", "胆汁", "出血"]
    },
    {
      "specialty": "neurosurgery",
      "keywords": ["颅", "脑", "神经", "脊髓", "头痛", "癫痫", "脑膜", "脑出血", "脑积水", "肿瘤"]
    },
    {
      "specialty": "orthopaedics",
      "keywords": ["骨", "骨折", "关节", "脊柱", "腰腿痛", "髋", "膝", "脱位", "创伤", "不能负重"]
    }
  ]
}
